cmdty_storage/__init__.py
cmdty_storage/__version__.py
cmdty_storage/_multi_factor_common.py
cmdty_storage/cmdty_storage.py
cmdty_storage/intrinsic.py
cmdty_storage/multi_factor.py
cmdty_storage/multi_factor_diffusion_model.py
cmdty_storage/multi_factor_spot_sim.py
cmdty_storage/time_func.py
cmdty_storage/trinomial.py
cmdty_storage/utils.py
cmdty_storage/lib/Cmdty.Core.Common.dll
cmdty_storage/lib/Cmdty.Core.Simulation.dll
cmdty_storage/lib/Cmdty.Core.Trees.dll
cmdty_storage/lib/Cmdty.Storage.dll
cmdty_storage/lib/Cmdty.Storage.pdb
cmdty_storage/lib/Cmdty.TimePeriodValueTypes.dll
cmdty_storage/lib/Cmdty.TimeSeries.dll
cmdty_storage/lib/JetBrains.Annotations.dll
cmdty_storage/lib/MathNet.Numerics.dll
cmdty_storage/lib/Microsoft.CSharp.dll
cmdty_storage/lib/Microsoft.CodeAnalysis.CSharp.Scripting.dll
cmdty_storage/lib/Microsoft.CodeAnalysis.CSharp.dll
cmdty_storage/lib/Microsoft.CodeAnalysis.Scripting.dll
cmdty_storage/lib/Microsoft.CodeAnalysis.dll
cmdty_storage/lib/Microsoft.Extensions.Logging.Abstractions.dll
cmdty_storage/lib/System.Buffers.dll
cmdty_storage/lib/System.Collections.Immutable.dll
cmdty_storage/lib/System.Dynamic.Runtime.dll
cmdty_storage/lib/System.Linq.Expressions.dll
cmdty_storage/lib/System.Linq.dll
cmdty_storage/lib/System.Memory.dll
cmdty_storage/lib/System.Numerics.Vectors.dll
cmdty_storage/lib/System.ObjectModel.dll
cmdty_storage/lib/System.Reflection.Emit.ILGeneration.dll
cmdty_storage/lib/System.Reflection.Emit.Lightweight.dll
cmdty_storage/lib/System.Reflection.Emit.dll
cmdty_storage/lib/System.Reflection.Metadata.dll
cmdty_storage/lib/System.Reflection.TypeExtensions.dll
cmdty_storage/lib/System.Runtime.CompilerServices.Unsafe.dll
cmdty_storage/lib/System.Text.Encoding.CodePages.dll
cmdty_storage/lib/System.Threading.Tasks.Extensions.dll
cmdty_storage/lib/System.Threading.dll
cmdty_storage/lib/x64/MathNet.Numerics.MKL.dll
cmdty_storage/lib/x64/libiomp5md.dll
cmdty_storage/lib/x86/MathNet.Numerics.MKL.dll
cmdty_storage-1.6.0.dist-info/LICENSE.md
cmdty_storage-1.6.0.dist-info/METADATA
cmdty_storage-1.6.0.dist-info/WHEEL
cmdty_storage-1.6.0.dist-info/top_level.txt
cmdty_storage-1.6.0.dist-info/RECORD
